powerconf/__init__.py
powerconf/cli.py
powerconf/exceptions.py
powerconf/expressions.py
powerconf/graphs.py
powerconf/loaders.py
powerconf/parallel_processing.py
powerconf/parsing.py
powerconf/pyyaml.py
powerconf/rendering.py
powerconf/units.py
powerconf/utils.py
powerconf/yaml.py
powerconf-0.7.0.dist-info/METADATA
powerconf-0.7.0.dist-info/WHEEL
powerconf-0.7.0.dist-info/entry_points.txt
powerconf-0.7.0.dist-info/RECORD
