Metadata-Version: 2.4
Name: powerconf
Version: 0.7.0
Summary: Powerup you configuration files.
Requires-Python: >=3.10
Requires-Dist: fspathtree>=1.0
Requires-Dist: networkx>=3.3
Requires-Dist: pint>=0.24.3
Requires-Dist: pyparsing>=3.1.4
Requires-Dist: pystache>=0.6.5
Requires-Dist: pyyaml>=6.0.2
Requires-Dist: typer>=0.12.5
